LICENSE
MANIFEST.in
README.md
setup.py
django_twitter_auth/__init__.py
django_twitter_auth/admin.py
django_twitter_auth/models.py
django_twitter_auth/urls.py
django_twitter_auth/views.py
django_twitter_auth/tests/__init__.py
django_twitter_auth/tests/__init__.pyc
django_twitter_auth/tests/test_models.py
django_twitter_auth/tests/test_models.pyc
django_twitter_auth/tests/test_views.py
django_twitter_auth/tests/test_views.pyc
simple_django_twitter_auth.egg-info/PKG-INFO
simple_django_twitter_auth.egg-info/SOURCES.txt
simple_django_twitter_auth.egg-info/dependency_links.txt
simple_django_twitter_auth.egg-info/requires.txt
simple_django_twitter_auth.egg-info/top_level.txt